xkcdrand/.__init__.py.un~
xkcdrand/__init__.py
xkcdrand-0.1.dist-info/METADATA
xkcdrand-0.1.dist-info/WHEEL
xkcdrand-0.1.dist-info/RECORD
