Metadata-Version: 1.2
Name: xkcdrand
Version: 0.1
Summary: a description
Home-page: https://github.com/Carreau/xkcdrand
License: UNKNOWN
Author: Matthias Bussonnier
Author-email: bussonniermatthias@gmail.com
Classifier: License :: OSI Approved :: MIT License
